microcore/main.py
microcore/cli/__init__.py
microcore/cli/execute.py
microcore/cli/commands/__init__.py
microcore/cli/commands/create_node.py
microcore/cli/commands/dockerize.py
microcore/cli/content/__init__.py
microcore/core/files/structmaster.py
micro_core_node-0.0.5.dist-info/METADATA
micro_core_node-0.0.5.dist-info/WHEEL
micro_core_node-0.0.5.dist-info/entry_points.txt
micro_core_node-0.0.5.dist-info/licenses/LICENSE
micro_core_node-0.0.5.dist-info/RECORD
