Metadata-Version: 2.3
Name: micro-core-node
Version: 0.0.5
Summary: Is training for self
Project-URL: Homepage, https://github.com/Micro-Core/MicroCore
Project-URL: Issues, https://github.com/Micro-Core/MicroCore
Author-email: Usmanov <usmnvk.work@gmail.com>
License-File: LICENSE
Classifier: License :: OSI Approved :: MIT License
Classifier: Operating System :: OS Independent
Classifier: Programming Language :: Python :: 3
Requires-Python: >=3.10.0
Requires-Dist: typer>=0.3.2
